setup.cfg
setup.py
traggrcl.py
traggr_api_client.egg-info/PKG-INFO
traggr_api_client.egg-info/SOURCES.txt
traggr_api_client.egg-info/dependency_links.txt
traggr_api_client.egg-info/requires.txt
traggr_api_client.egg-info/top_level.txt