Metadata-Version: 1.0
Name: traggr-api-client
Version: 0.2.1
Summary: API client for Test Results Aggregation system
Home-page: https://github.com/witalick/traggr-api-client
Author: Vitaliy Yakoviv
Author-email: witalick@gmail.com
License: UNKNOWN
Keywords: api,testing
Platform: UNKNOWN
